pyclovaocr/__init__.py
pyclovaocr/ocr.py
pyclovaocr-1.0.dist-info/LICENSE
pyclovaocr-1.0.dist-info/METADATA
pyclovaocr-1.0.dist-info/WHEEL
pyclovaocr-1.0.dist-info/top_level.txt
pyclovaocr-1.0.dist-info/RECORD
