Metadata-Version: 2.1
Name: pyclovaocr
Version: 1.0
Summary: Unofficial Clova AI OCR python wrapper
Home-page: https://github.com/kdrkdrkdr/pyclovaocr
Author: kdr
Author-email: kdrhacker1234@gmail.com
License: MIT
Platform: UNKNOWN
Classifier: Programming Language :: Python :: 3
Classifier: License :: OSI Approved :: MIT License
Classifier: Operating System :: OS Independent
Requires-Dist: requests
